statslibx/__init__.py
statslibx/cli.py
statslibx/descriptive.py
statslibx/inferential.py
statslibx/io.py
statslibx/utils.py
statslibx/datasets/__init__.py
statslibx/datasets/course_completion.csv
statslibx/datasets/iris.csv
statslibx/datasets/penguins.csv
statslibx/datasets/sp500_companies.csv
statslibx/datasets/titanic.csv
statslibx/preprocessing/__init__.py
statslibx-0.1.7.dist-info/METADATA
statslibx-0.1.7.dist-info/WHEEL
statslibx-0.1.7.dist-info/entry_points.txt
statslibx-0.1.7.dist-info/top_level.txt
statslibx-0.1.7.dist-info/RECORD
