Metadata-Version: 2.4
Name: statslibx
Version: 0.1.7
Summary: StatsLibx - Librería de estadística descriptiva e inferencial
Author-email: Emmanuel Ascendra Perez <ascendraemmanuel@gmail.com>
License: MIT
Classifier: Development Status :: 3 - Alpha
Classifier: Intended Audience :: Science/Research
Classifier: Topic :: Scientific/Engineering :: Mathematics
Classifier: License :: OSI Approved :: MIT License
Classifier: Programming Language :: Python :: 3
Classifier: Programming Language :: Python :: 3.9
Classifier: Programming Language :: Python :: 3.10
Classifier: Programming Language :: Python :: 3.11
Classifier: Programming Language :: Python :: 3.12
Requires-Python: >=3.8
Requires-Dist: pandas>=1.5
Requires-Dist: polars>=0.20
Provides-Extra: viz
Requires-Dist: seaborn>=0.11; extra == "viz"
Requires-Dist: plotly>=5.0; extra == "viz"
Provides-Extra: advanced
Requires-Dist: scikit-learn>=1.0; extra == "advanced"
Requires-Dist: statsmodels>=0.13; extra == "advanced"
